Workbook

Sheet Common
A1: Common Inputs
A3: Used by workbook formulas
A5: Input | B5: Value
A7: Bps per unit | B7: 10000
A9: Risk watch NPA threshold | B9: 0.03
A11: Currency unit | B11: INR crore (Cr)
A12: Data note | B12: Fictional / illustrative training data - not actual Axis Bank figures

Sheet Branch Flows
A1: Date | B1: Product Line | C1: Product | D1: Sub-Product | E1: Customer Segment | F1: Region (Zone) | G1: Channel | H1: Opening Balance (Rs Cr) | I1: Net Flows (Rs Cr) | J1: Growth Rate | K1: Spread / Fee (bps) | L1: Closing Balance (Rs Cr) | M1: Estimated Annual Income (Rs Cr) | N1: Flow % of Opening | O1: Income Yield (bps)
A2: 46053 | B2: Retail Deposits | C2: Savings Account | D2: Regular Savings | E2: Salaried Retail | F2: North | G2: Branch | H2: 12500 | I2: 420 | J2: 0.012 | K2: 62 | L2: =H2*(1+J2)+I2 -> 13070 | M2: =L2*K2/Common!$B$7 -> 81.034 | N2: =IF(H2=0,0,I2/H2) -> 0.0336 | O2: =IF(L2=0,0,M2/L2*Common!$B$7) -> 62
A3: 46053 | B3: Retail Deposits | C3: Current Account | D3: Business Current | E3: Self-Employed / MSME | F3: West | G3: Branch | H3: 6800 | I3: 210 | J3: 0.008 | K3: 78 | L3: =H3*(1+J3)+I3 -> 7064.4 | M3: =L3*K3/Common!$B$7 -> 55.10232 | N3: =IF(H3=0,0,I3/H3) -> 0.030882353 | O3: =IF(L3=0,0,M3/L3*Common!$B$7) -> 78
A4: 46053 | B4: Retail Lending | C4: Home Loan | D4: Prime Housing | E4: Salaried Retail | F4: South | G4: DSA/Partner | H4: 18400 | I4: 640 | J4: 0.01 | K4: 45 | L4: =H4*(1+J4)+I4 -> 19224 | M4: =L4*K4/Common!$B$7 -> 86.508 | N4: =IF(H4=0,0,I4/H4) -> 0.034782609 | O4: =IF(L4=0,0,M4/L4*Common!$B$7) -> 45
A5: 46053 | B5: Cards & Payments | C5: Credit Cards | D5: Premium Cards | E5: Priority | F5: West | G5: Digital/Mobile Banking | H5: 3200 | I5: 180 | J5: 0.015 | K5: 92 | L5: =H5*(1+J5)+I5 -> 3428 | M5: =L5*K5/Common!$B$7 -> 31.5376 | N5: =IF(H5=0,0,I5/H5) -> 0.05625 | O5: =IF(L5=0,0,M5/L5*Common!$B$7) -> 92
A6: 46053 | B6: Corporate Banking | C6: Working Capital | D6: Cash Credit | E6: Large Corporate | F6: West | G6: Corporate RM | H6: 22500 | I6: -340 | J6: 0.004 | K6: 38 | L6: =H6*(1+J6)+I6 -> 22250 | M6: =L6*K6/Common!$B$7 -> 84.55 | N6: =IF(H6=0,0,I6/H6) -> -0.015111111 | O6: =IF(L6=0,0,M6/L6*Common!$B$7) -> 38
A7: 46081 | B7: Retail Deposit | C7: Fixed Deposit | D7: Retail Term Deposit | E7: NRI | F7: North | G7: Digital/Mobile Banking | H7: 9400 | I7: 510 | J7: 0.011 | K7: 26 | L7: =H7*(1+J7)+I7 -> 10013.4 | M7: =L7*K7/Common!$B$7 -> 26.03484 | N7: =IF(H7=0,0,I7/H7) -> 0.054255319 | O7: =IF(L7=0,0,M7/L7*Common!$B$7) -> 26
A8: 46081 | B8: Retail Lending | C8: Personal Loan | D8: Unsecured PL | E8: Salaried Retail | F8: Central | G8: Digital/Mobile Banking | H8: 4100 | I8: 265 | J8: 0.018 | K8: 88 | L8: =H8*(1+J8)+I8 -> 4438.8 | M8: =L8*K8/Common!$B$7 -> 39.06144 | N8: =IF(H8=0,0,I8/H8) -> 0.064634146 | O8: =IF(L8=0,0,M8/L8*Common!$B$7) -> 88
A9: 46081 | B9: Cards and Payments | C9: UPI/Merchant Acquiring | D9: Merchant QR | E9: Self-Employed / MSME | F9: South | G9: Digital/Mobile Banking | H9: 2750 | I9: 195 | J9: 0.022 | K9: 34 | L9: =H9*(1+J9)+I9 -> 3005.5 | M9: =L9*K9/Common!$B$7 -> 10.2187 | N9: =IF(H9=0,0,I9/H9) -> 0.070909091 | O9: =IF(L9=0,0,M9/L9*Common!$B$7) -> 34
A10: 46081 | B10: Wealth & Third-Party Distribution | C10: Mutual Fund Distribution | D10: SIP Book | E10: Burgundy | F10: West | G10: Branch | H10: 5600 | I10: 320 | J10: 0.014 | K10: 72 | L10: =H10*(1+J10)+I10 -> 5998.4 | M10: =L10*K10/Common!$B$7 -> 43.18848 | N10: =IF(H10=0,0,I10/H10) -> 0.057142857 | O10: =IF(L10=0,0,M10/L10*Common!$B$7) -> 72
A11: 46081 | B11: Rural & Inclusive Banking | C11: Kisan Credit | D11: KCC Renewal | E11: Rural/Agri | F11: East | G11: Business Correspondent | H11: 1850 | I11: 95 | J11: 0.009 | K11: 41 | L11: =H11*(1+J11)+I11 -> 1961.65 | M11: =L11*K11/Common!$B$7 -> 8.042765 | N11: =IF(H11=0,0,I11/H11) -> 0.051351351 | O11: =IF(L11=0,0,M11/L11*Common!$B$7) -> 41
A12: 46112 | B12: Retail Deposits | C12: Savings Account | D12: Priority Savings | E12: Priority | F12: South | G12: Branch | H12: 8900 | I12: 260 | J12: 0.01 | K12: 58 | L12: =H12*(1+J12)+I12 -> 9249 | M12: =L12*K12/Common!$B$7 -> 53.6442 | N12: =IF(H12=0,0,I12/H12) -> 0.029213483 | O12: =IF(L12=0,0,M12/L12*Common!$B$7) -> 58
A13: 46112 | B13: Retail Lending | C13: Auto Loan | D13: New Car | E13: Salaried Retail | F13: North | G13: DSA/Partner | H13: 5300 | I13: 240 | J13: 0.013 | K13: 51 | L13: =H13*(1+J13)+I13 -> 5608.9 | M13: =L13*K13/Common!$B$7 -> 28.60539 | N13: =IF(H13=0,0,I13/H13) -> 0.045283019 | O13: =IF(L13=0,0,M13/L13*Common!$B$7) -> 51
... A24: 46203 | B24: Retail Lending | C24: Personal Loan | D24: Top-up PL | E24: Priority | F24: West | G24: Contact Centre | H24: 3600 | I24: 175 | J24: 0.015 | K24: 83 | L24: =H24*(1+J24)+I24 -> 3829 | M24: =L24*K24/Common!$B$7 -> 31.7807 | N24: =IF(H24=0,0,I24/H24) -> 0.048611111 | O24: =IF(L24=0,0,M24/L24*Common!$B$7) -> 83
A25: 46053 | B25: Retail Lending | C25: Home Loan | D25: Prime Housing | E25: Salaried Retail | F25: South | G25: DSA/Partner | H25: 18400 | I25: 640 | J25: 0.01 | K25: 45 | L25: 19224 | M25: 86.508 | N25: 0.034783 | O25: 45
A26: 46081 | B26: Wealth & Third-Party Distribution | C26: Mutual Fund Distribution | D26: SIP Book | E26: Burgundy | F26: West | G26: Branch | H26: 5600 | I26: 320 | J26: 0.014 | K26: 72 | L26: 5998.4 | M26: 43.1885 | N26: 0.057143 | O26: 72
A27: 46203 | B27: Cards & Payments | C27: UPI/Merchant Acquiring | D27: Merchant QR | E27: Self-Employed / MSME | F27: South | G27: Digital/Mobile Banking | H27: 2600 | I27: 48500 | J27: 0.021 | K27: 170 | L27: =H27*(1+J27)+I27 -> 51154.6 | M27: =L27*K27/Common!$B$7 -> 869.6282 | N27: =IF(H27=0,0,I27/H27) -> 18.653846 | O27: =IF(L27=0,0,M27/L27*Common!$B$7) -> 170

Sheet Customer Segments
A1: Customer Segment | B1: Region | C1: Relationship Tier | D1: Products Held | E1: Balances (Rs Cr) | F1: Average Spread (bps) | G1: Annual Income (Rs Cr) | H1: Net New Balances YTD (Rs Cr) | I1: Cross-sell Priority | J1: Relationship Health Score (0-100)
A2: Burgundy Private | B2: North | C2: Tier 1 - Private | D2: 7 | E2: 9800 | F2: 74 | G2: =E2*F2/Common!$B$7 -> 72.52 | H2: 540 | I2: High | J2: 88
A3: Burgundy Private | B3: West | C3: Tier 1 - Private | D3: 6 | E3: 8450 | F3: 71 | G3: =E3*F3/Common!$B$7 -> 59.995 | H3: 410 | I3: High | J3: 85
A4: Burgundy | B4: South | C4: Tier 2 - Affluent | D4: 5 | E4: 7200 | F4: 66 | G4: =E4*F4/Common!$B$7 -> 47.52 | H4: 325 | I4: High | J4: 79
A5: Burgundy | B5: West | C5: Tier 2 - Affluent | D5: 5 | E5: 6350 | F5: 63 | G5: =E5*F5/Common!$B$7 -> 40.005 | H5: 280 | I5: Medium | J5: 76
A6: Priority | B6: North | C6: Tier 3 - Priority | D6: 4 | E6: 5900 | F6: 58 | G6: =E6*F6/Common!$B$7 -> 34.22 | H6: 240 | I6: Medium | J6: 72
A7: Priority | B7: Central | C7: Tier 3 - Priority | D7: 4 | E7: 4750 | F7: 55 | G7: =E7*F7/Common!$B$7 -> 26.125 | H7: 185 | I7: Medium | J7: 70
A8: Salaried Retail | B8: South | C8: Tier 4 - Mass Affluent | D8: 3 | E8: 11200 | F8: 49 | G8: =E8*F8/Common!$B$7 -> 54.88 | H8: 520 | I8: High | J8: 68
A9: Salaried Retail | B9: East | C9: Tier 4 - Mass Affluent | D9: 3 | E9: 6800 | F9: 47 | G9: =E9*F9/Common!$B$7 -> 31.96 | H9: 310 | I9: Medium | J9: 64
A10: Self-Employed / MSME | B10: West | C10: Tier 3 - Business | D10: 4 | E10: 8900 | F10: 81 | G10: =E10*F10/Common!$B$7 -> 72.09 | H10: 395 | I10: High | J10: 71
A11: Large Corporate | B11: West | C11: Tier 1 - Institutional | D11: 6 | E11: 24500 | F11: 36 | G11: =E11*F11/Common!$B$7 -> 88.2 | H11: 880 | I11: Medium | J11: 82
A12: NRI | B12: North | C12: Tier 2 - NRI | D12: 4 | E12: 7650 | F12: 43 | G12: =E12*F12/Common!$B$7 -> 32.895 | H12: 295 | I12: Medium | J12: 75
A13: Rural/Agri | B13: East | C13: Tier 5 - Inclusive | D13: 2 | E13: 3100 | F13: 64 | G13: =E13*F13/Common!$B$7 -> 19.84 | H13: 140 | I13: Low | J13: 58

Sheet Risk Metrics
A1: Portfolio | B1: Product Line | C1: Benchmark (peer/industry) | D1: Portfolio Yield | E1: Benchmark Yield | F1: Active Spread | G1: Gross NPA % | H1: Credit Cost % | I1: PCR / Coverage Ratio | J1: Risk-Adjusted Ratio | K1: Risk Rating
A2: Savings Account Book | B2: Retail Deposits | C2: Private bank peer set | D2: 0.0315 | E2: 0.0298 | F2: =D2-E2 -> 0.0017 | G2: 0.0042 | H2: 0.006 | I2: 0.78 | J2: =IF(H2=0,0,F2/H2) -> 0.28333333 | K2: Low
A3: Fixed Deposit Book | B3: Retail Deposits | C3: Industry term deposit | D3: 0.069 | E3: 0.0672 | F3: =D3-E3 -> 0.0018 | G3: 0.0018 | H3: 0.0025 | I3: 0.82 | J3: =IF(H3=0,0,F3/H3) -> 0.72 | K3: Low
A4: Home Loan | B4: Retail Lending | C4: Housing finance peer index | D4: 0.0885 | E4: 0.0862 | F4: =D4-E4 -> 0.0023 | G4: 0.0112 | H4: 0.0038 | I4: 0.71 | J4: =IF(H4=0,0,F4/H4) -> 0.60526316 | K4: Low
A5: Auto Loan | B5: Retail Lending | C5: Retail auto peer set | D5: 0.094 | E5: 0.0925 | F5: =D5-E5 -> 0.0015 | G5: 0.0148 | H5: 0.0072 | I5: 0.68 | J5: =IF(H5=0,0,F5/H5) -> 0.20833333 | K5: Medium
A6: Personal Loan | B6: Retail Lending | C6: Unsecured retail index | D6: 0.152 | E6: 0.1465 | F6: =D6-E6 -> 0.0055 | G6: 0.0325 | H6: 0.021 | I6: 0.64 | J6: =IF(H6=0,0,F6/H6) -> 0.26190476 | K6: High
A7: Credit Cards | B7: Cards & Payments | C7: Card industry benchmark | D7: 0.218 | E7: 0.2095 | F7: =D7-E7 -> 0.0085 | G7: 0.029 | H7: 0.0245 | I7: 0.66 | J7: =IF(H7=0,0,F7/H7) -> 0.34693878 | K7: High
A8: UPI / Merchant Acquiring | B8: Cards & Payments | C8: Acquirer peer set | D8: 0.018 | E8: 0.0172 | F8: =D8-E8 -> 0.0008 | G8: 0.0055 | H8: 0.0031 | I8: 0.74 | J8: =IF(H8=0,0,F8/H8) -> 0.25806452 | K8: Medium
A9: Working Capital | B9: Corporate Banking | C9: Large corporate index | D9: 0.0865 | E9: 0.0848 | F9: =D9-E9 -> 0.0017 | G9: 0.0185 | H9: 0.0068 | I9: 0.75 | J9: =IF(H9=0,0,F9/H9) -> 0.25 | K9: Medium
A10: Trade Finance | B10: Corporate Banking | C10: Trade credit benchmark | D10: 0.0725 | E10: 0.0718 | F10: =D10-E10 -> 0.0007 | G10: 0.0092 | H10: 0.0029 | I10: 0.8 | J10: =IF(H10=0,0,F10/H10) -> 0.24137931 | K10: Low
A11: Bancassurance Book | B11: Wealth & Third-Party Distribution | C11: Distribution peer set | D11: 0.045 | E11: 0.0438 | F11: =D11-E11 -> 0.0012 | G11: 0.0021 | H11: 0.0012 | I11: 0.85 | J11: =IF(H11=0,0,F11/H11) -> 1 | K11: Low
A12: Kisan Credit | B12: Rural & Inclusive Banking | C12: Agri lending index | D12: 0.091 | E12: 0.0895 | F12: =D12-E12 -> 0.0015 | G12: 0.041 | H12: 0.0185 | I12: 0.62 | J12: =IF(H12=0,0,F12/H12) -> 0.081081081 | K12: High
A13: Microfinance | B13: Rural & Inclusive Banking | C13: MFI industry index | D13: 0.1985 | E13: 0.192 | F13: =D13-E13 -> 0.0065 | G13: 0.0362 | H13: 0.0248 | I13: 0.6 | J13: =IF(H13=0,0,F13/H13) -> 0.26209677 | K13: High

Sheet Summary
A1: Executive Banking Snapshot
A3: Total closing balances (Rs Cr) | B3: =SUM('Branch Flows'!L2:L27) -> 258197.83
A4: Total YTD net flows (Rs Cr) | B4: =SUM('Branch Flows'!I2:I27) -> 54753
A5: Estimated annual income (Rs Cr) | B5: =SUM('Branch Flows'!M2:M27) -> 1917.8427
A6: Average flow rate | B6: =AVERAGE('Branch Flows'!N2:N27) -> 0.75745765
A7: Weighted growth rate | B7: =SUMPRODUCT('Branch Flows'!L2:L27,'Branch Flows'!J2:J27)/SUM('Branch Flows'!L2:L27) -> 0.012093624
A8: Top income product line | B8: =INDEX($D$12:$D$17,MATCH(MAX($G$12:$G$17),$G$12:$G$17,0)) -> Cards & Payments
D10: Product Line Summary
D11: Product Line | E11: Net Flows (Rs Cr) | F11: Closing Balance (Rs Cr) | G11: Est. Annual Income (Rs Cr)
D12: Retail Deposits | E12: =SUMIF('Branch Flows'!$B$2:$B$27,$D12,'Branch Flows'!$I$2:$I$27) -> 1150 | F12: =SUMIF('Branch Flows'!$B$2:$B$27,$D12,'Branch Flows'!$L$2:$L$27) -> 45626.6 | G12: =SUMIF('Branch Flows'!$B$2:$B$27,$D12,'Branch Flows'!$M$2:$M$27) -> 276.39553
D13: Retail Lending | E13: =SUMIF('Branch Flows'!$B$2:$B$27,$D13,'Branch Flows'!$I$2:$I$27) -> 2005 | F13: =SUMIF('Branch Flows'!$B$2:$B$27,$D13,'Branch Flows'!$L$2:$L$27) -> 55178.7 | G13: =SUMIF('Branch Flows'!$B$2:$B$27,$D13,'Branch Flows'!$M$2:$M$27) -> 267.67825
D14: Cards & Payments | E14: =SUMIF('Branch Flows'!$B$2:$B$27,$D14,'Branch Flows'!$I$2:$I$27) -> 48810 | F14: =SUMIF('Branch Flows'!$B$2:$B$27,$D14,'Branch Flows'!$L$2:$L$27) -> 57201.8 | G14: =SUMIF('Branch Flows'!$B$2:$B$27,$D14,'Branch Flows'!$M$2:$M$27) -> 924.7386
D15: Corporate Banking | E15: =SUMIF('Branch Flows'!$B$2:$B$27,$D15,'Branch Flows'!$I$2:$I$27) -> 560 | F15: =SUMIF('Branch Flows'!$B$2:$B$27,$D15,'Branch Flows'!$L$2:$L$27) -> 57373.8 | G15: =SUMIF('Branch Flows'!$B$2:$B$27,$D15,'Branch Flows'!$M$2:$M$27) -> 194.59246
D16: Wealth & Third-Party Distribution | E16: =SUMIF('Branch Flows'!$B$2:$B$27,$D16,'Branch Flows'!$I$2:$I$27) -> 925 | F16: =SUMIF('Branch Flows'!$B$2:$B$27,$D16,'Branch Flows'!$L$2:$L$27) -> 18461.1 | G16: =SUMIF('Branch Flows'!$B$2:$B$27,$D16,'Branch Flows'!$M$2:$M$27) -> 130.33422
D17: Rural & Inclusive Banking | E17: =SUMIF('Branch Flows'!$B$2:$B$27,$D17,'Branch Flows'!$I$2:$I$27) -> 183 | F17: =SUMIF('Branch Flows'!$B$2:$B$27,$D17,'Branch Flows'!$L$2:$L$27) -> 3310.73 | G17: =SUMIF('Branch Flows'!$B$2:$B$27,$D17,'Branch Flows'!$M$2:$M$27) -> 18.295773
D18: Total (canonical spellings only) | E18: =SUM(E12:E17) -> 53633 | F18: =SUM(F12:F17) -> 237152.73 | G18: =SUM(G12:G17) -> 1812.0348
D20: Note: totals above exclude mis-spelt product-line variants in Branch Flows - a Copilot data-cleaning exercise.
